{
	"name": "adls_dataset_for_senario_errorhandle",
	"properties": {
		"linkedServiceName": {
			"referenceName": "ls adls storage for dataflow",
			"type": "LinkedServiceReference"
		},
		"parameters": {
			"container_name": {
				"type": "string"
			},
			"folder_name": {
				"type": "string"
			},
			"file_name": {
				"type": "string"
			}
		},
		"annotations": [],
		"type": "DelimitedText",
		"typeProperties": {
			"location": {
				"type": "AzureBlobStorageLocation",
				"fileName": {
					"value": "@dataset().file_name",
					"type": "Expression"
				},
				"folderPath": {
					"value": "@dataset().folder_name",
					"type": "Expression"
				},
				"container": {
					"value": "@dataset().container_name",
					"type": "Expression"
				}
			},
			"columnDelimiter": ",",
			"escapeChar": "\\",
			"firstRowAsHeader": true,
			"quoteChar": "\""
		},
		"schema": [
			{
				"name": "salesDate",
				"type": "String"
			},
			{
				"name": "salesItem",
				"type": "String"
			},
			{
				"name": "country",
				"type": "String"
			},
			{
				"name": "quantity",
				"type": "String"
			}
		]
	},
	"type": "Microsoft.DataFactory/factories/datasets"
}